[{"place_id": 233942567, "licence": "Data \u00a9 OpenStreetMap contributors, ODbL 1.0. http://osm.org/copyright", "osm_type": "node", "osm_id": 11460900240, "lat": "8.4807528", "lon": "76.9128833", "class": "highway", "type": "bus_stop", "place_rank": 30, "importance": 6.407034409089826e-05, "addresstype": "highway", "name": "Shangumugham", "display_name": "Shangumugham, Veli -Perumathura Road, Vallakkadavu, Thiruvananthapuram, Kerala, 695001, India", "boundingbox": ["8.4807028", "8.4808028", "76.9128333", "76.9129333"]}]